cdk_ecs_public_discovery/__init__.py
cdk_ecs_public_discovery/py.typed
cdk_ecs_public_discovery/_jsii/__init__.py
cdk_ecs_public_discovery/_jsii/cdk-ecs-public-discovery@1.0.1.jsii.tgz
cdk_ecs_public_discovery-1.0.1.dist-info/LICENSE
cdk_ecs_public_discovery-1.0.1.dist-info/METADATA
cdk_ecs_public_discovery-1.0.1.dist-info/WHEEL
cdk_ecs_public_discovery-1.0.1.dist-info/top_level.txt
cdk_ecs_public_discovery-1.0.1.dist-info/RECORD
