Metadata-Version: 2.1
Name: cdk-ecs-public-discovery
Version: 1.0.1
Summary: An AWS CDK library that provides ECS service discovery functionality for an ECS task's public IP address
Home-page: https://github.com/engineal/cdk-ecs-public-discovery#readme
Author: Aaron Lucia
License: Apache-2.0
Project-URL: Source, https://github.com/engineal/cdk-ecs-public-discovery.git
Platform: UNKNOWN
Classifier: Intended Audience :: Developers
Classifier: Operating System :: OS Independent
Classifier: Programming Language :: JavaScript
Classifier: Programming Language :: Python :: 3 :: Only
Classifier: Programming Language :: Python :: 3.7
Classifier: Programming Language :: Python :: 3.8
Classifier: Programming Language :: Python :: 3.9
Classifier: Programming Language :: Python :: 3.10
Classifier: Typing :: Typed
Classifier: Development Status :: 4 - Beta
Classifier: License :: OSI Approved
Requires-Python: ~=3.7
License-File: LICENSE
Requires-Dist: aws-cdk-lib (==2.65.0)
Requires-Dist: constructs (<11.0.0,>=10.0.0)
Requires-Dist: jsii (<2.0.0,>=1.75.0)
Requires-Dist: publication (>=0.0.3)
Requires-Dist: typeguard (~=2.13.3)
